edea_ms/__init__.py
edea_ms/__main__.py
edea_ms/main.py
edea_ms/core/auth.py
edea_ms/core/authz.py
edea_ms/core/helpers.py
edea_ms/core/staticfiles.py
edea_ms/db/__init__.py
edea_ms/db/models.py
edea_ms/db/queries.py
edea_ms/db/alembic/env.py
edea_ms/db/alembic/versions/577b56b7f3de_rename_value_hidden_to_setpoint_hidden.py
edea_ms/db/alembic/versions/7c67fc371bc8_initial_schema.py
edea_ms/db/alembic/versions/a73209e4df83_add_hidden_flag_to_forcing_conditions.py
edea_ms/routers/__init__.py
edea_ms/routers/auth_oidc.py
edea_ms/routers/config.py
edea_ms/routers/export.py
edea_ms/routers/files.py
edea_ms/routers/forcing_condition.py
edea_ms/routers/jobs.py
edea_ms/routers/measurement_columns.py
edea_ms/routers/measurement_entries.py
edea_ms/routers/projects.py
edea_ms/routers/specifications.py
edea_ms/routers/testruns.py
edea_ms/routers/users.py
edea_ms/static/favicon-16x16.png
edea_ms/static/favicon-32x32.png
edea_ms/static/favicon.ico
edea_ms/static/icon.svg
edea_ms/static/index.html
edea_ms/static/_app/env.js
edea_ms/static/_app/version.json
edea_ms/static/_app/immutable/assets/0.FFmk7yxy.css
edea_ms/static/_app/immutable/assets/3.BMIWPGx3.css
edea_ms/static/_app/immutable/assets/ProgressBar.c6i8ireL.css
edea_ms/static/_app/immutable/assets/SimpleTable.Dkss2u5Q.css
edea_ms/static/_app/immutable/assets/_layout.74uMfbY4.css
edea_ms/static/_app/immutable/assets/codicon.DCmgc-ay.ttf
edea_ms/static/_app/immutable/chunks/3.BIY6VRVe.js
edea_ms/static/_app/immutable/chunks/Icon.Dh0Pc4QJ.js
edea_ms/static/_app/immutable/chunks/ProgressBar.svelte_svelte_type_style_lang.CPHjajrS.js
edea_ms/static/_app/immutable/chunks/SimpleTable.3mU2w9X0.js
edea_ms/static/_app/immutable/chunks/VegaLite.9NT-XMw_.js
edea_ms/static/_app/immutable/chunks/abap.BrgZPUOV.js
edea_ms/static/_app/immutable/chunks/apex.DyP6w7ZV.js
edea_ms/static/_app/immutable/chunks/azcli.BaLxmfj-.js
edea_ms/static/_app/immutable/chunks/bat.CFOPXBzS.js
edea_ms/static/_app/immutable/chunks/bicep.BfEKNvv3.js
edea_ms-0.3.0.dist-info/METADATA
edea_ms-0.3.0.dist-info/WHEEL
edea_ms-0.3.0.dist-info/licenses/LICENSE.frontend.txt
edea_ms-0.3.0.dist-info/licenses/LICENSE.txt
edea_ms-0.3.0.dist-info/RECORD
