Metadata-Version: 2.3
Name: edea_ms
Version: 0.3.0
Summary: EDeA Measurement Server
Author-email: Elen Eisendle <ln@calcifer.ee>
License:                       EUROPEAN UNION PUBLIC LICENCE v. 1.2
Requires-Python: <3.13,>=3.11
Requires-Dist: aiofiles
Requires-Dist: aiosqlite
Requires-Dist: alembic
Requires-Dist: authlib>=1.3.2
Requires-Dist: cryptography
Requires-Dist: fastapi>=0.115.6
Requires-Dist: httpx
Requires-Dist: itsdangerous
Requires-Dist: polars
Requires-Dist: pyarrow
Requires-Dist: pyjwt
Requires-Dist: python-multipart
Requires-Dist: sqlalchemy[asyncio]>=2.0.36
Requires-Dist: uvicorn[standard]>=0.32.1
Provides-Extra: charts
Requires-Dist: altair>=5.5.0; extra == 'charts'
Requires-Dist: vl-convert-python>=1.7.0; extra == 'charts'
